icost_app_mcp_server/__init__.py
icost_app_mcp_server/cli.py
icost_app_mcp_server/py.typed
icost_app_mcp_server/server.py
icost_app_mcp_server-0.2.1.dist-info/licenses/LICENSE
icost_app_mcp_server-0.2.1.dist-info/METADATA
icost_app_mcp_server-0.2.1.dist-info/WHEEL
icost_app_mcp_server-0.2.1.dist-info/entry_points.txt
icost_app_mcp_server-0.2.1.dist-info/top_level.txt
icost_app_mcp_server-0.2.1.dist-info/RECORD
