Metadata-Version: 2.4
Name: icost-app-mcp-server
Version: 0.2.1
Summary: 一个基于 FastMCP 2.0 框架构建的模型上下文协议（MCP）服务，专为 iCost iOS 记账应用提供智能记账功能集成。
Author-email: "jason.tang.dev" <json.tang.dev@gmail.com>
Maintainer-email: "jason.tang.dev" <json.tang.dev@gmail.com>
License:                                  Apache License
Project-URL: Homepage, https://github.com/TooLife/icost-app-mcp-server
Project-URL: Documentation, https://github.com/TooLife/icost-app-mcp-server
Project-URL: Repository, https://github.com/TooLife/icost-app-mcp-server
Project-URL: Bug Tracker, https://github.com/TooLife/icost-app-mcp-server/issues
Keywords: mcp,model-context-protocol,icost,server,fastmcp
Classifier: Development Status :: 3 - Alpha
Classifier: Intended Audience :: Developers
Classifier: License :: OSI Approved :: MIT License
Classifier: Operating System :: OS Independent
Classifier: Programming Language :: Python :: 3.10
Classifier: Programming Language :: Python :: 3.11
Classifier: Programming Language :: Python :: 3.12
Classifier: Topic :: Software Development :: Libraries :: Python Modules
Classifier: Topic :: Internet :: WWW/HTTP :: HTTP Servers
Requires-Python: >=3.10
License-File: LICENSE
Requires-Dist: fastmcp>=2.0.0
Requires-Dist: uvicorn[standard]>=0.23.0
Provides-Extra: dev
Requires-Dist: pytest>=7.0.0; extra == "dev"
Requires-Dist: pytest-cov>=4.0.0; extra == "dev"
Requires-Dist: pytest-asyncio>=0.21.0; extra == "dev"
Requires-Dist: black>=23.0.0; extra == "dev"
Requires-Dist: isort>=5.12.0; extra == "dev"
Requires-Dist: flake8>=6.0.0; extra == "dev"
Requires-Dist: mypy>=1.0.0; extra == "dev"
Requires-Dist: pre-commit>=3.0.0; extra == "dev"
Requires-Dist: tox>=4.0.0; extra == "dev"
Provides-Extra: docs
Requires-Dist: sphinx>=7.0.0; extra == "docs"
Requires-Dist: sphinx-rtd-theme>=1.3.0; extra == "docs"
Requires-Dist: sphinx-autodoc-typehints>=1.24.0; extra == "docs"
Provides-Extra: test
Requires-Dist: pytest>=7.0.0; extra == "test"
Requires-Dist: pytest-cov>=4.0.0; extra == "test"
Requires-Dist: pytest-asyncio>=0.21.0; extra == "test"
Requires-Dist: coverage>=7.0.0; extra == "test"
Dynamic: license-file
